{
  "brasileirao": {
    "name": "Brasileirao",
    "flag": "BR",
    "category_id": "3878608",
    "products": [
      {
        "name": "Portuguesa",
        "image": "https://photo.yupoo.com/1to1jerseyworld/ab8b337f/medium.jpg",
        "link": "https://1to1jerseyworld.x.yupoo.com/albums/197838807?uid=1&isSubCate=false&referrercate=3878608",
        "price": null
      },
      {
        "name": "Volta Redonda",
        "image": "brasileirão/Volta_Redonda_Futebol_Clube.svg.png",
        "link": "https://1to1jerseyworld.x.yupoo.com/albums/191401113?uid=1&isSubCate=false&referrercate=3878608",
        "price": null
      },
      {
        "name": "Esporte Clube Juventude",
        "image": "brasileirão/EC_Juventude.svg.png",
        "link": "https://1to1jerseyworld.x.yupoo.com/albums/181804312?uid=1&isSubCate=false&referrercate=3878608",
        "price": null
      },
      {
        "name": "Cuiabá Esporte Clube",
        "image": "https://photo.yupoo.com/1to1jerseyworld/88b0167f/medium.jpg",
        "link": "https://1to1jerseyworld.x.yupoo.com/albums/167232417?uid=1&isSubCate=false&referrercate=3878608",
        "price": null
      },
      {
        "name": "Confiança FC（信任）",
        "image": "https://photo.yupoo.com/1to1jerseyworld/73c90fb7/medium.jpg",
        "link": "https://1to1jerseyworld.x.yupoo.com/albums/163398275?uid=1&isSubCate=false&referrercate=3878608",
        "price": null
      },
      {
        "name": "Coritiba PR",
        "image": "https://photo.yupoo.com/1to1jerseyworld/250f017f/medium.jpg",
        "link": "https://1to1jerseyworld.x.yupoo.com/albums/149865507?uid=1&isSubCate=false&referrercate=3878608",
        "price": null
      },
      {
        "name": "Criciuma SC",
        "image": "https://photo.yupoo.com/1to1jerseyworld/1f6dc361/medium.jpeg",
        "link": "https://1to1jerseyworld.x.yupoo.com/albums/140889378?uid=1&isSubCate=false&referrercate=3878608",
        "price": null
      },
      {
        "name": "Santa Cruz",
        "image": "brasileirão/Santa_Cruz_Futebol_Clube_(1915-99).png",
        "link": "https://1to1jerseyworld.x.yupoo.com/albums/139336836?uid=1&isSubCate=false&referrercate=3878608",
        "price": null
      },
      {
        "name": "Chapecoense",
        "image": "https://photo.yupoo.com/1to1jerseyworld/86c84576/medium.jpg",
        "link": "https://1to1jerseyworld.x.yupoo.com/albums/137834569?uid=1&isSubCate=false&referrercate=3878608",
        "price": null
      },
      {
        "name": "Vitória Salvador BA",
        "image": "https://photo.yupoo.com/1to1jerseyworld/82253cff/medium.jpg",
        "link": "https://1to1jerseyworld.x.yupoo.com/albums/133715311?uid=1&isSubCate=false&referrercate=3878608",
        "price": null
      },
      {
        "name": "Paysandu Sport Club",
        "image": "brasileirão/PaysanduSC.png",
        "link": "https://1to1jerseyworld.x.yupoo.com/albums/133197828?uid=1&isSubCate=false&referrercate=3878608",
        "price": null
      },
      {
        "name": "Clube do Remo",
        "image": "https://photo.yupoo.com/1to1jerseyworld/933c7d02/medium.jpg",
        "link": "https://1to1jerseyworld.x.yupoo.com/albums/133197813?uid=1&isSubCate=false&referrercate=3878608",
        "price": null
      },
      {
        "name": "Guarani",
        "image": "brasileirão/Guarani_Futebol_Clube_logo.svg.png",
        "link": "https://1to1jerseyworld.x.yupoo.com/albums/132753352?uid=1&isSubCate=false&referrercate=3878608",
        "price": null
      },
      {
        "name": "Ceara SC CE",
        "image": "https://photo.yupoo.com/1to1jerseyworld/fd37add3/medium.jpg",
        "link": "https://1to1jerseyworld.x.yupoo.com/albums/116274041?uid=1&isSubCate=false&referrercate=3878608",
        "price": null
      },
      {
        "name": "Avai FC",
        "image": "https://photo.yupoo.com/1to1jerseyworld/a436a29c/medium.jpg",
        "link": "https://1to1jerseyworld.x.yupoo.com/albums/115703934?uid=1&isSubCate=false&referrercate=3878608",
        "price": null
      },
      {
        "name": "America MG",
        "image": "brasileirão/Escudo_oficial_do_América_Futebol_Clube.svg.png",
        "link": "https://1to1jerseyworld.x.yupoo.com/albums/115397303?uid=1&isSubCate=false&referrercate=3878608",
        "price": null
      },
      {
        "name": "Fortaleza",
        "image": "https://photo.yupoo.com/1to1jerseyworld/672590ab/medium.jpg",
        "link": "https://1to1jerseyworld.x.yupoo.com/albums/113343793?uid=1&isSubCate=false&referrercate=3878608",
        "price": null
      },
      {
        "name": "Bahia",
        "image": "https://photo.yupoo.com/1to1jerseyworld/d6dccb3a/medium.jpg",
        "link": "https://1to1jerseyworld.x.yupoo.com/albums/112015342?uid=1&isSubCate=false&referrercate=3878608",
        "price": null
      },
      {
        "name": "brazil",
        "image": "https://photo.yupoo.com/1to1jerseyworld/4b900288/medium.jpg",
        "link": "https://1to1jerseyworld.x.yupoo.com/albums/112016394?uid=1&isSubCate=false&referrercate=3878608",
        "price": null
      },
      {
        "name": "Flamengo",
        "image": "https://photo.yupoo.com/1to1jerseyworld/4736eb41/medium.jpg",
        "link": "https://1to1jerseyworld.x.yupoo.com/albums/112015493?uid=1&isSubCate=false&referrercate=3878608",
        "price": null
      },
      {
        "name": "Fluminense",
        "image": "https://photo.yupoo.com/1to1jerseyworld/73b607fe/medium.jpg",
        "link": "https://1to1jerseyworld.x.yupoo.com/albums/112015503?uid=1&isSubCate=false&referrercate=3878608",
        "price": null
      },
      {
        "name": "Vasco da Gama",
        "image": "https://photo.yupoo.com/1to1jerseyworld/c4f6012d/medium.jpg",
        "link": "https://1to1jerseyworld.x.yupoo.com/albums/112015488?uid=1&isSubCate=false&referrercate=3878608",
        "price": null
      },
      {
        "name": "Internacional",
        "image": "https://photo.yupoo.com/1to1jerseyworld/5c4509f3/medium.jpg",
        "link": "https://1to1jerseyworld.x.yupoo.com/albums/112015322?uid=1&isSubCate=false&referrercate=3878608",
        "price": null
      },
      {
        "name": "Botafogo",
        "image": "https://photo.yupoo.com/1to1jerseyworld/4f775d0d/medium.jpg",
        "link": "https://1to1jerseyworld.x.yupoo.com/albums/112015474?uid=1&isSubCate=false&referrercate=3878608",
        "price": null
      },
      {
        "name": "Gremio",
        "image": "brasileirão/Gremio_logo.svg.png",
        "link": "https://1to1jerseyworld.x.yupoo.com/albums/112015518?uid=1&isSubCate=false&referrercate=3878608",
        "price": null
      },
      {
        "name": "Corinthians",
        "image": "https://photo.yupoo.com/1to1jerseyworld/c8954a4e/medium.jpg",
        "link": "https://1to1jerseyworld.x.yupoo.com/albums/112015526?uid=1&isSubCate=false&referrercate=3878608",
        "price": null
      },
      {
        "name": "Cruzeiro",
        "image": "https://photo.yupoo.com/1to1jerseyworld/7d883a23/medium.jpg",
        "link": "https://1to1jerseyworld.x.yupoo.com/albums/112015533?uid=1&isSubCate=false&referrercate=3878608",
        "price": null
      },
      {
        "name": "Atletico Mineiro",
        "image": "https://photo.yupoo.com/1to1jerseyworld/e36b0c54/medium.jpg",
        "link": "https://1to1jerseyworld.x.yupoo.com/albums/112015543?uid=1&isSubCate=false&referrercate=3878608",
        "price": null
      },
      {
        "name": "Palmeiras",
        "image": "brasileirão/Palmeiras_logo.svg.png",
        "link": "https://1to1jerseyworld.x.yupoo.com/albums/112015549?uid=1&isSubCate=false&referrercate=3878608",
        "price": null
      },
      {
        "name": "Santos",
        "image": "brasileirão/Santos_logo.svg.png",
        "link": "https://1to1jerseyworld.x.yupoo.com/albums/112015554?uid=1&isSubCate=false&referrercate=3878608",
        "price": null
      },
      {
        "name": "São Paulo",
        "image": "https://photo.yupoo.com/1to1jerseyworld/586b0f50/medium.jpg",
        "link": "https://1to1jerseyworld.x.yupoo.com/albums/112015561?uid=1&isSubCate=false&referrercate=3878608",
        "price": null
      },
      {
        "name": "Atlético Paranaense",
        "image": "https://photo.yupoo.com/1to1jerseyworld/4c14e035/medium.jpg",
        "link": "https://1to1jerseyworld.x.yupoo.com/albums/112015694?uid=1&isSubCate=false&referrercate=3878608",
        "price": null
      },
      {
        "name": "Bragantino",
        "image": "brasileirão/RedBullBragantino.png",
        "link": "https://1to1jerseyworld.x.yupoo.com/albums/112015765?uid=1&isSubCate=false&referrercate=3878608",
        "price": null
      },
      {
        "name": "Recife",
        "image": "https://photo.yupoo.com/1to1jerseyworld/975a0ccd/medium.jpg",
        "link": "https://1to1jerseyworld.x.yupoo.com/albums/112015892?uid=1&isSubCate=false&referrercate=3878608",
        "price": null
      },
      {
        "name": "Náutico Capibaribe",
        "image": "https://photo.yupoo.com/1to1jerseyworld/80d6bfe1/medium.jpg",
        "link": "https://1to1jerseyworld.x.yupoo.com/albums/112016335?uid=1&isSubCate=false&referrercate=3878608",
        "price": null
      }
    ],
    "count": 35
  },
  "premier-league": {
    "name": "Premier League",
    "flag": "EN",
    "category_id": "3879265",
    "products": [
      {
        "name": "Burnley",
        "image": "https://photo.yupoo.com/1to1jerseyworld/dae30f73/medium.jpg",
        "link": "https://1to1jerseyworld.x.yupoo.com/albums/208836258?uid=1&isSubCate=false&referrercate=3879265",
        "price": null
      },
      {
        "name": "Middlesbrough",
        "image": "https://photo.yupoo.com/1to1jerseyworld/b948d5e4/medium.jpg",
        "link": "https://1to1jerseyworld.x.yupoo.com/albums/206578173?uid=1&isSubCate=false&referrercate=3879265",
        "price": null
      },
      {
        "name": "Birmingham City",
        "image": "https://photo.yupoo.com/1to1jerseyworld/3e2a96b7/medium.jpg",
        "link": "https://1to1jerseyworld.x.yupoo.com/albums/206568756?uid=1&isSubCate=false&referrercate=3879265",
        "price": null
      },
      {
        "name": "Plymouth Argyle",
        "image": "https://photo.yupoo.com/1to1jerseyworld/25ecbc02/medium.jpg",
        "link": "https://1to1jerseyworld.x.yupoo.com/albums/200444821?uid=1&isSubCate=false&referrercate=3879265",
        "price": null
      },
      {
        "name": "Bradford City",
        "image": "https://photo.yupoo.com/1to1jerseyworld/94f27e57/medium.jpg",
        "link": "https://1to1jerseyworld.x.yupoo.com/albums/200269321?uid=1&isSubCate=false&referrercate=3879265",
        "price": null
      },
      {
        "name": "Preston North End",
        "image": "https://photo.yupoo.com/1to1jerseyworld/dc574fcd/medium.jpg",
        "link": "https://1to1jerseyworld.x.yupoo.com/albums/177995210?uid=1&isSubCate=false&referrercate=3879265",
        "price": null
      },
      {
        "name": "Portsmouth",
        "image": "https://photo.yupoo.com/1to1jerseyworld/59189a05/medium.jpg",
        "link": "https://1to1jerseyworld.x.yupoo.com/albums/172999588?uid=1&isSubCate=false&referrercate=3879265",
        "price": null
      },
      {
        "name": "Wrexham",
        "image": "https://photo.yupoo.com/1to1jerseyworld/148640fa/medium.jpg",
        "link": "https://1to1jerseyworld.x.yupoo.com/albums/172694286?uid=1&isSubCate=false&referrercate=3879265",
        "price": null
      },
      {
        "name": "Lincoln City",
        "image": "https://photo.yupoo.com/1to1jerseyworld/c341df97/medium.jpg",
        "link": "https://1to1jerseyworld.x.yupoo.com/albums/172115516?uid=1&isSubCate=false&referrercate=3879265",
        "price": null
      },
      {
        "name": "Bolton Wanderers",
        "image": "https://photo.yupoo.com/1to1jerseyworld/60483caf/medium.jpg",
        "link": "https://1to1jerseyworld.x.yupoo.com/albums/172115262?uid=1&isSubCate=false&referrercate=3879265",
        "price": null
      },
      {
        "name": "Norwich City",
        "image": "https://photo.yupoo.com/1to1jerseyworld/dd86e51c/medium.jpg",
        "link": "https://1to1jerseyworld.x.yupoo.com/albums/171886973?uid=1&isSubCate=false&referrercate=3879265",
        "price": null
      },
      {
        "name": "Derby County",
        "image": "https://photo.yupoo.com/1to1jerseyworld/fb526f15/medium.jpg",
        "link": "https://1to1jerseyworld.x.yupoo.com/albums/170451979?uid=1&isSubCate=false&referrercate=3879265",
        "price": null
      },
      {
        "name": "Ipswich Town",
        "image": "https://photo.yupoo.com/1to1jerseyworld/e50045d5/medium.jpg",
        "link": "https://1to1jerseyworld.x.yupoo.com/albums/170451905?uid=1&isSubCate=false&referrercate=3879265",
        "price": null
      },
      {
        "name": "Sheffield Wednesday",
        "image": "https://photo.yupoo.com/1to1jerseyworld/2319eec3/medium.jpg",
        "link": "https://1to1jerseyworld.x.yupoo.com/albums/168952718?uid=1&isSubCate=false&referrercate=3879265",
        "price": null
      },
      {
        "name": "Sunderland AFC",
        "image": "https://photo.yupoo.com/1to1jerseyworld/7667ba7e/medium.jpg",
        "link": "https://1to1jerseyworld.x.yupoo.com/albums/167230302?uid=1&isSubCate=false&referrercate=3879265",
        "price": null
      },
      {
        "name": "AFC Bournemouth",
        "image": "https://photo.yupoo.com/1to1jerseyworld/2c3939f0/medium.jpg",
        "link": "https://1to1jerseyworld.x.yupoo.com/albums/166842072?uid=1&isSubCate=false&referrercate=3879265",
        "price": null
      },
      {
        "name": "Southampton",
        "image": "https://photo.yupoo.com/1to1jerseyworld/1df901b7/medium.jpg",
        "link": "https://1to1jerseyworld.x.yupoo.com/albums/140466041?uid=1&isSubCate=false&referrercate=3879265",
        "price": null
      },
      {
        "name": "Watford F.C.",
        "image": "https://photo.yupoo.com/1to1jerseyworld/60976845/medium.jpg",
        "link": "https://1to1jerseyworld.x.yupoo.com/albums/140255388?uid=1&isSubCate=false&referrercate=3879265",
        "price": null
      },
      {
        "name": "Cardiff City F.C.",
        "image": "https://photo.yupoo.com/1to1jerseyworld/cb4b0722/medium.jpg",
        "link": "https://1to1jerseyworld.x.yupoo.com/albums/140255375?uid=1&isSubCate=false&referrercate=3879265",
        "price": null
      },
      {
        "name": "Fulham",
        "image": "https://photo.yupoo.com/1to1jerseyworld/a7c8457e/medium.jpg",
        "link": "https://1to1jerseyworld.x.yupoo.com/albums/139412990?uid=1&isSubCate=false&referrercate=3879265",
        "price": null
      },
      {
        "name": "加密相册",
        "image": "https://photo.yupoo.com/1to1jerseyworld/a0b7d002/medium.jpg",
        "link": "https://1to1jerseyworld.x.yupoo.com",
        "price": null
      },
      {
        "name": "加密相册",
        "image": "https://photo.yupoo.com/1to1jerseyworld/d1eb98fb/medium.jpg",
        "link": "https://1to1jerseyworld.x.yupoo.com",
        "price": null
      },
      {
        "name": "加密相册",
        "image": "https://photo.yupoo.com/1to1jerseyworld/e9d77ea3/medium.jpg",
        "link": "https://1to1jerseyworld.x.yupoo.com",
        "price": null
      },
      {
        "name": "Sheffield United",
        "image": "https://photo.yupoo.com/1to1jerseyworld/ba9a0574/medium.jpeg",
        "link": "https://1to1jerseyworld.x.yupoo.com/albums/136600126?uid=1&isSubCate=false&referrercate=3879265",
        "price": null
      },
      {
        "name": "Nottingham Forest",
        "image": "https://photo.yupoo.com/1to1jerseyworld/0ab3687b/medium.jpeg",
        "link": "https://1to1jerseyworld.x.yupoo.com/albums/134401856?uid=1&isSubCate=false&referrercate=3879265",
        "price": null
      },
      {
        "name": "Brighton",
        "image": "https://photo.yupoo.com/1to1jerseyworld/2f5e2043/medium.jpg",
        "link": "https://1to1jerseyworld.x.yupoo.com/albums/122255736?uid=1&isSubCate=false&referrercate=3879265",
        "price": null
      },
      {
        "name": "Manchester United",
        "image": "https://photo.yupoo.com/1to1jerseyworld/eed8866e/medium.jpg",
        "link": "https://1to1jerseyworld.x.yupoo.com/albums/112067763?uid=1&isSubCate=false&referrercate=3879265",
        "price": null
      },
      {
        "name": "Manchester City",
        "image": "https://photo.yupoo.com/1to1jerseyworld/93827ba5/medium.jpg",
        "link": "https://1to1jerseyworld.x.yupoo.com/albums/112067849?uid=1&isSubCate=false&referrercate=3879265",
        "price": null
      },
      {
        "name": "Arsenal",
        "image": "https://photo.yupoo.com/1to1jerseyworld/b7dd0f87/medium.jpg",
        "link": "https://1to1jerseyworld.x.yupoo.com/albums/112067743?uid=1&isSubCate=false&referrercate=3879265",
        "price": null
      },
      {
        "name": "Everton",
        "image": "https://photo.yupoo.com/1to1jerseyworld/e545f3c0/medium.jpg",
        "link": "https://1to1jerseyworld.x.yupoo.com/albums/112067722?uid=1&isSubCate=false&referrercate=3879265",
        "price": null
      },
      {
        "name": "Leicester City",
        "image": "https://photo.yupoo.com/1to1jerseyworld/882118b5/medium.jpg",
        "link": "https://1to1jerseyworld.x.yupoo.com/albums/112067704?uid=1&isSubCate=false&referrercate=3879265",
        "price": null
      },
      {
        "name": "Wolves",
        "image": "https://photo.yupoo.com/1to1jerseyworld/8e28134c/medium.jpg",
        "link": "https://1to1jerseyworld.x.yupoo.com/albums/112067677?uid=1&isSubCate=false&referrercate=3879265",
        "price": null
      },
      {
        "name": "Chelsea",
        "image": "https://photo.yupoo.com/1to1jerseyworld/d08fa240/medium.jpg",
        "link": "https://1to1jerseyworld.x.yupoo.com/albums/112067619?uid=1&isSubCate=false&referrercate=3879265",
        "price": null
      },
      {
        "name": "Leeds United",
        "image": "https://photo.yupoo.com/1to1jerseyworld/6e04f237/medium.jpg",
        "link": "https://1to1jerseyworld.x.yupoo.com/albums/112067580?uid=1&isSubCate=false&referrercate=3879265",
        "price": null
      },
      {
        "name": "Newcastle",
        "image": "https://photo.yupoo.com/1to1jerseyworld/da247b43/medium.jpg",
        "link": "https://1to1jerseyworld.x.yupoo.com/albums/112067489?uid=1&isSubCate=false&referrercate=3879265",
        "price": null
      },
      {
        "name": "Tottenham",
        "image": "https://photo.yupoo.com/1to1jerseyworld/94337476/medium.jpg",
        "link": "https://1to1jerseyworld.x.yupoo.com/albums/112067457?uid=1&isSubCate=false&referrercate=3879265",
        "price": null
      },
      {
        "name": "Crystal Palace",
        "image": "https://photo.yupoo.com/1to1jerseyworld/82ee1489/medium.jpg",
        "link": "https://1to1jerseyworld.x.yupoo.com/albums/112067439?uid=1&isSubCate=false&referrercate=3879265",
        "price": null
      },
      {
        "name": "Aston Villa",
        "image": "https://photo.yupoo.com/1to1jerseyworld/1ee0a756/medium.jpg",
        "link": "https://1to1jerseyworld.x.yupoo.com/albums/112067390?uid=1&isSubCate=false&referrercate=3879265",
        "price": null
      },
      {
        "name": "West Ham United",
        "image": "https://photo.yupoo.com/1to1jerseyworld/6f01b0b1/medium.jpg",
        "link": "https://1to1jerseyworld.x.yupoo.com/albums/112067327?uid=1&isSubCate=false&referrercate=3879265",
        "price": null
      },
      {
        "name": "West Brom",
        "image": "https://photo.yupoo.com/1to1jerseyworld/01e2bd37/medium.jpg",
        "link": "https://1to1jerseyworld.x.yupoo.com/albums/112067349?uid=1&isSubCate=false&referrercate=3879265",
        "price": null
      }
    ],
    "count": 40
  },
  "la-liga": {
    "name": "La Liga",
    "flag": "ES",
    "category_id": "3879374",
    "products": [
      {
        "name": "Cartagena",
        "image": "https://photo.yupoo.com/1to1jerseyworld/c2ddff3d/medium.jpg",
        "link": "https://1to1jerseyworld.x.yupoo.com/albums/218960892?uid=1&isSubCate=false&referrercate=3879374",
        "price": null
      },
      {
        "name": "Levante",
        "image": "https://photo.yupoo.com/1to1jerseyworld/f3c50f7a/medium.jpg",
        "link": "https://1to1jerseyworld.x.yupoo.com/albums/208836452?uid=1&isSubCate=false&referrercate=3879374",
        "price": null
      },
      {
        "name": "Burgos",
        "image": "https://photo.yupoo.com/1to1jerseyworld/57224379/medium.jpg",
        "link": "https://1to1jerseyworld.x.yupoo.com/albums/208836196?uid=1&isSubCate=false&referrercate=3879374",
        "price": null
      },
      {
        "name": "Ceuta",
        "image": "https://photo.yupoo.com/1to1jerseyworld/8e492532/medium.jpg",
        "link": "https://1to1jerseyworld.x.yupoo.com/albums/201418706?uid=1&isSubCate=false&referrercate=3879374",
        "price": null
      },
      {
        "name": "Hércules",
        "image": "https://photo.yupoo.com/1to1jerseyworld/477e3a05/medium.jpg",
        "link": "https://1to1jerseyworld.x.yupoo.com/albums/194753447?uid=1&isSubCate=false&referrercate=3879374",
        "price": null
      },
      {
        "name": "Murcia",
        "image": "https://photo.yupoo.com/1to1jerseyworld/b15bbb1c/medium.jpg",
        "link": "https://1to1jerseyworld.x.yupoo.com/albums/189031626?uid=1&isSubCate=false&referrercate=3879374",
        "price": null
      },
      {
        "name": "Racing de Santander",
        "image": "https://photo.yupoo.com/1to1jerseyworld/5a1f6ad8/medium.jpg",
        "link": "https://1to1jerseyworld.x.yupoo.com/albums/180534782?uid=1&isSubCate=false&referrercate=3879374",
        "price": null
      },
      {
        "name": "Mallorca",
        "image": "https://photo.yupoo.com/1to1jerseyworld/d8032c5f/medium.jpg",
        "link": "https://1to1jerseyworld.x.yupoo.com/albums/179269250?uid=1&isSubCate=false&referrercate=3879374",
        "price": null
      },
      {
        "name": "Getafe",
        "image": "https://photo.yupoo.com/1to1jerseyworld/c444a002/medium.jpg",
        "link": "https://1to1jerseyworld.x.yupoo.com/albums/174082306?uid=1&isSubCate=false&referrercate=3879374",
        "price": null
      },
      {
        "name": "Sporting de Gijón",
        "image": "https://photo.yupoo.com/1to1jerseyworld/7ebc39a7/medium.jpg",
        "link": "https://1to1jerseyworld.x.yupoo.com/albums/173001469?uid=1&isSubCate=false&referrercate=3879374",
        "price": null
      },
      {
        "name": "Almeria",
        "image": "https://photo.yupoo.com/1to1jerseyworld/659bc3ec/medium.jpg",
        "link": "https://1to1jerseyworld.x.yupoo.com/albums/172693923?uid=1&isSubCate=false&referrercate=3879374",
        "price": null
      },
      {
        "name": "Albacete",
        "image": "https://photo.yupoo.com/1to1jerseyworld/a215a9e9/medium.jpg",
        "link": "https://1to1jerseyworld.x.yupoo.com/albums/172693822?uid=1&isSubCate=false&referrercate=3879374",
        "price": null
      },
      {
        "name": "Cordoba",
        "image": "https://photo.yupoo.com/1to1jerseyworld/7a5f38be/medium.jpg",
        "link": "https://1to1jerseyworld.x.yupoo.com/albums/171596722?uid=1&isSubCate=false&referrercate=3879374",
        "price": null
      },
      {
        "name": "Zaragoza",
        "image": "https://photo.yupoo.com/1to1jerseyworld/ddf19be0/medium.jpg",
        "link": "https://1to1jerseyworld.x.yupoo.com/albums/169110300?uid=1&isSubCate=false&referrercate=3879374",
        "price": null
      },
      {
        "name": "Tenerife",
        "image": "https://photo.yupoo.com/1to1jerseyworld/ff6bf345/medium.jpg",
        "link": "https://1to1jerseyworld.x.yupoo.com/albums/168846401?uid=1&isSubCate=false&referrercate=3879374",
        "price": null
      },
      {
        "name": "Oviedo FC",
        "image": "https://photo.yupoo.com/1to1jerseyworld/d2b34147/medium.jpg",
        "link": "https://1to1jerseyworld.x.yupoo.com/albums/168834538?uid=1&isSubCate=false&referrercate=3879374",
        "price": null
      },
      {
        "name": "Celta de Vigo",
        "image": "https://photo.yupoo.com/1to1jerseyworld/888271cf/medium.jpg",
        "link": "https://1to1jerseyworld.x.yupoo.com/albums/168030458?uid=1&isSubCate=false&referrercate=3879374",
        "price": null
      },
      {
        "name": "Deportivo La Coruna",
        "image": "https://photo.yupoo.com/1to1jerseyworld/1dfa036b/medium.jpg",
        "link": "https://1to1jerseyworld.x.yupoo.com/albums/166070122?uid=1&isSubCate=false&referrercate=3879374",
        "price": null
      },
      {
        "name": "Girona",
        "image": "https://photo.yupoo.com/1to1jerseyworld/eed7f32b/medium.jpg",
        "link": "https://1to1jerseyworld.x.yupoo.com/albums/150516808?uid=1&isSubCate=false&referrercate=3879374",
        "price": null
      },
      {
        "name": "Rayo Vallecano",
        "image": "https://photo.yupoo.com/1to1jerseyworld/e9fd3f94/medium.jpg",
        "link": "https://1to1jerseyworld.x.yupoo.com/albums/143659645?uid=1&isSubCate=false&referrercate=3879374",
        "price": null
      },
      {
        "name": "Las Palmas",
        "image": "https://photo.yupoo.com/1to1jerseyworld/99fed065/medium.jpg",
        "link": "https://1to1jerseyworld.x.yupoo.com/albums/120388120?uid=1&isSubCate=false&referrercate=3879374",
        "price": null
      },
      {
        "name": "Leganes",
        "image": "https://photo.yupoo.com/1to1jerseyworld/c3ae7049/medium.jpg",
        "link": "https://1to1jerseyworld.x.yupoo.com/albums/119635537?uid=1&isSubCate=false&referrercate=3879374",
        "price": null
      },
      {
        "name": "Malaga CF",
        "image": "https://photo.yupoo.com/1to1jerseyworld/64021252/medium.jpg",
        "link": "https://1to1jerseyworld.x.yupoo.com/albums/119635147?uid=1&isSubCate=false&referrercate=3879374",
        "price": null
      },
      {
        "name": "RCD Espanyol",
        "image": "https://photo.yupoo.com/1to1jerseyworld/fe81bcc8/medium.jpg",
        "link": "https://1to1jerseyworld.x.yupoo.com/albums/119329852?uid=1&isSubCate=false&referrercate=3879374",
        "price": null
      },
      {
        "name": "Barcelona",
        "image": "https://photo.yupoo.com/1to1jerseyworld/194dc717/medium.jpg",
        "link": "https://1to1jerseyworld.x.yupoo.com/albums/112075982?uid=1&isSubCate=false&referrercate=3879374",
        "price": null
      },
      {
        "name": "Real Madrid",
        "image": "https://photo.yupoo.com/1to1jerseyworld/be3d65d5/medium.jpg",
        "link": "https://1to1jerseyworld.x.yupoo.com/albums/112075927?uid=1&isSubCate=false&referrercate=3879374",
        "price": null
      },
      {
        "name": "Atletico Madrid",
        "image": "https://photo.yupoo.com/1to1jerseyworld/d9e6f67c/medium.jpg",
        "link": "https://1to1jerseyworld.x.yupoo.com/albums/112075910?uid=1&isSubCate=false&referrercate=3879374",
        "price": null
      },
      {
        "name": "Valencia",
        "image": "https://photo.yupoo.com/1to1jerseyworld/273f5bb1/medium.jpg",
        "link": "https://1to1jerseyworld.x.yupoo.com/albums/112075893?uid=1&isSubCate=false&referrercate=3879374",
        "price": null
      },
      {
        "name": "Sevilla",
        "image": "https://photo.yupoo.com/1to1jerseyworld/7a45fbb9/medium.jpg",
        "link": "https://1to1jerseyworld.x.yupoo.com/albums/112075902?uid=1&isSubCate=false&referrercate=3879374",
        "price": null
      },
      {
        "name": "Betis",
        "image": "https://photo.yupoo.com/1to1jerseyworld/f237043b/medium.jpg",
        "link": "https://1to1jerseyworld.x.yupoo.com/albums/112075972?uid=1&isSubCate=false&referrercate=3879374",
        "price": null
      },
      {
        "name": "Alaves",
        "image": "https://photo.yupoo.com/1to1jerseyworld/402af316/medium.jpg",
        "link": "https://1to1jerseyworld.x.yupoo.com/albums/112076036?uid=1&isSubCate=false&referrercate=3879374",
        "price": null
      },
      {
        "name": "Elche",
        "image": "https://photo.yupoo.com/1to1jerseyworld/4cc7413f/medium.jpg",
        "link": "https://1to1jerseyworld.x.yupoo.com/albums/112076021?uid=1&isSubCate=false&referrercate=3879374",
        "price": null
      },
      {
        "name": "Osasuna",
        "image": "https://photo.yupoo.com/1to1jerseyworld/bb785053/medium.jpg",
        "link": "https://1to1jerseyworld.x.yupoo.com/albums/112076013?uid=1&isSubCate=false&referrercate=3879374",
        "price": null
      },
      {
        "name": "Valladolid",
        "image": "https://photo.yupoo.com/1to1jerseyworld/8e894d72/medium.jpg",
        "link": "https://1to1jerseyworld.x.yupoo.com/albums/112075999?uid=1&isSubCate=false&referrercate=3879374",
        "price": null
      },
      {
        "name": "Villarreal",
        "image": "https://photo.yupoo.com/1to1jerseyworld/924a12c4/medium.jpg",
        "link": "https://1to1jerseyworld.x.yupoo.com/albums/112075965?uid=1&isSubCate=false&referrercate=3879374",
        "price": null
      },
      {
        "name": "Athletic Bilbao",
        "image": "https://photo.yupoo.com/1to1jerseyworld/1ff65726/medium.jpg",
        "link": "https://1to1jerseyworld.x.yupoo.com/albums/112075948?uid=1&isSubCate=false&referrercate=3879374",
        "price": null
      },
      {
        "name": "Real Sociedad",
        "image": "https://photo.yupoo.com/1to1jerseyworld/bacbae9e/medium.jpg",
        "link": "https://1to1jerseyworld.x.yupoo.com/albums/112075929?uid=1&isSubCate=false&referrercate=3879374",
        "price": null
      },
      {
        "name": "Granada",
        "image": "https://photo.yupoo.com/1to1jerseyworld/a9f5ffc9/medium.jpg",
        "link": "https://1to1jerseyworld.x.yupoo.com/albums/112075934?uid=1&isSubCate=false&referrercate=3879374",
        "price": null
      },
      {
        "name": "Cadiz",
        "image": "https://photo.yupoo.com/1to1jerseyworld/4425592d/medium.jpg",
        "link": "https://1to1jerseyworld.x.yupoo.com/albums/112075918?uid=1&isSubCate=false&referrercate=3879374",
        "price": null
      },
      {
        "name": "Huesca",
        "image": "https://photo.yupoo.com/1to1jerseyworld/741502ea/medium.jpg",
        "link": "https://1to1jerseyworld.x.yupoo.com/albums/112075885?uid=1&isSubCate=false&referrercate=3879374",
        "price": null
      }
    ],
    "count": 40
  },
  "serie-a": {
    "name": "Serie A",
    "flag": "IT",
    "category_id": "3879491",
    "products": [
      {
        "name": "US Cremonese",
        "image": "https://photo.yupoo.com/1to1jerseyworld/fb584bed/medium.jpg",
        "link": "https://1to1jerseyworld.x.yupoo.com/albums/215598138?uid=1&isSubCate=false&referrercate=3879491",
        "price": null
      },
      {
        "name": "Sorrento Calcio 1945",
        "image": "https://photo.yupoo.com/1to1jerseyworld/d7bab712/medium.jpg",
        "link": "https://1to1jerseyworld.x.yupoo.com/albums/208836079?uid=1&isSubCate=false&referrercate=3879491",
        "price": null
      },
      {
        "name": "Palermo",
        "image": "https://photo.yupoo.com/1to1jerseyworld/c7bfa81d/medium.jpg",
        "link": "https://1to1jerseyworld.x.yupoo.com/albums/197838554?uid=1&isSubCate=false&referrercate=3879491",
        "price": null
      },
      {
        "name": "Hellas Verona",
        "image": "https://photo.yupoo.com/1to1jerseyworld/c7f14ea7/medium.jpg",
        "link": "https://1to1jerseyworld.x.yupoo.com/albums/195434522?uid=1&isSubCate=false&referrercate=3879491",
        "price": null
      },
      {
        "name": "Como 1907",
        "image": "https://photo.yupoo.com/1to1jerseyworld/3367a0c3/medium.jpg",
        "link": "https://1to1jerseyworld.x.yupoo.com/albums/195118558?uid=1&isSubCate=false&referrercate=3879491",
        "price": null
      },
      {
        "name": "加密相册",
        "image": "https://photo.yupoo.com/1to1jerseyworld/e5c4c60b/medium.jpg",
        "link": "https://1to1jerseyworld.x.yupoo.com",
        "price": null
      },
      {
        "name": "加密相册",
        "image": "https://photo.yupoo.com/1to1jerseyworld/fd83f29d/medium.jpg",
        "link": "https://1to1jerseyworld.x.yupoo.com",
        "price": null
      },
      {
        "name": "加密相册",
        "image": "https://photo.yupoo.com/1to1jerseyworld/bcd0e619/medium.jpg",
        "link": "https://1to1jerseyworld.x.yupoo.com",
        "price": null
      },
      {
        "name": "Brescia Calcio",
        "image": "https://photo.yupoo.com/1to1jerseyworld/fb1cd0ea/medium.jpg",
        "link": "https://1to1jerseyworld.x.yupoo.com/albums/183278322?uid=1&isSubCate=false&referrercate=3879491",
        "price": null
      },
      {
        "name": "Bologna",
        "image": "https://photo.yupoo.com/1to1jerseyworld/d091217f/medium.jpg",
        "link": "https://1to1jerseyworld.x.yupoo.com/albums/182426368?uid=1&isSubCate=false&referrercate=3879491",
        "price": null
      },
      {
        "name": "Genoa CFC",
        "image": "https://photo.yupoo.com/1to1jerseyworld/f4c8c9b8/medium.jpg",
        "link": "https://1to1jerseyworld.x.yupoo.com/albums/177995086?uid=1&isSubCate=false&referrercate=3879491",
        "price": null
      },
      {
        "name": "Venezia F.C.",
        "image": "https://photo.yupoo.com/1to1jerseyworld/50578b60/medium.jpg",
        "link": "https://1to1jerseyworld.x.yupoo.com/albums/118623830?uid=1&isSubCate=false&referrercate=3879491",
        "price": null
      },
      {
        "name": "AC Milan",
        "image": "https://photo.yupoo.com/1to1jerseyworld/8c60c242/medium.jpg",
        "link": "https://1to1jerseyworld.x.yupoo.com/albums/112090486?uid=1&isSubCate=false&referrercate=3879491",
        "price": null
      },
      {
        "name": "Inter Milan",
        "image": "https://photo.yupoo.com/1to1jerseyworld/889cb69e/medium.jpg",
        "link": "https://1to1jerseyworld.x.yupoo.com/albums/112090272?uid=1&isSubCate=false&referrercate=3879491",
        "price": null
      },
      {
        "name": "Roma",
        "image": "https://photo.yupoo.com/1to1jerseyworld/fc962ed8/medium.jpg",
        "link": "https://1to1jerseyworld.x.yupoo.com/albums/112090361?uid=1&isSubCate=false&referrercate=3879491",
        "price": null
      },
      {
        "name": "Napoli",
        "image": "https://photo.yupoo.com/1to1jerseyworld/8758b355/medium.jpg",
        "link": "https://1to1jerseyworld.x.yupoo.com/albums/112090351?uid=1&isSubCate=false&referrercate=3879491",
        "price": null
      },
      {
        "name": "parma",
        "image": "https://photo.yupoo.com/1to1jerseyworld/72429101/medium.jpg",
        "link": "https://1to1jerseyworld.x.yupoo.com/albums/112090368?uid=1&isSubCate=false&referrercate=3879491",
        "price": null
      },
      {
        "name": "Atalanta",
        "image": "https://photo.yupoo.com/1to1jerseyworld/827c9752/medium.jpg",
        "link": "https://1to1jerseyworld.x.yupoo.com/albums/112090341?uid=1&isSubCate=false&referrercate=3879491",
        "price": null
      },
      {
        "name": "Sampdoria",
        "image": "https://photo.yupoo.com/1to1jerseyworld/44ec12bd/medium.jpg",
        "link": "https://1to1jerseyworld.x.yupoo.com/albums/112090329?uid=1&isSubCate=false&referrercate=3879491",
        "price": null
      },
      {
        "name": "Sassuolo",
        "image": "https://photo.yupoo.com/1to1jerseyworld/a038690b/medium.jpg",
        "link": "https://1to1jerseyworld.x.yupoo.com/albums/112090314?uid=1&isSubCate=false&referrercate=3879491",
        "price": null
      },
      {
        "name": "Lazio",
        "image": "https://photo.yupoo.com/1to1jerseyworld/af80ef16/medium.jpg",
        "link": "https://1to1jerseyworld.x.yupoo.com/albums/112090304?uid=1&isSubCate=false&referrercate=3879491",
        "price": null
      },
      {
        "name": "Fiorentina",
        "image": "https://photo.yupoo.com/1to1jerseyworld/4fe0d944/medium.jpg",
        "link": "https://1to1jerseyworld.x.yupoo.com/albums/112090262?uid=1&isSubCate=false&referrercate=3879491",
        "price": null
      },
      {
        "name": "Torino",
        "image": "https://photo.yupoo.com/1to1jerseyworld/c6b9b0c6/medium.jpg",
        "link": "https://1to1jerseyworld.x.yupoo.com/albums/112090253?uid=1&isSubCate=false&referrercate=3879491",
        "price": null
      },
      {
        "name": "Cagliari",
        "image": "https://photo.yupoo.com/1to1jerseyworld/0d073381/medium.jpg",
        "link": "https://1to1jerseyworld.x.yupoo.com/albums/112090285?uid=1&isSubCate=false&referrercate=3879491",
        "price": null
      },
      {
        "name": "Spezia",
        "image": "https://photo.yupoo.com/1to1jerseyworld/19cfde8f/medium.jpg",
        "link": "https://1to1jerseyworld.x.yupoo.com/albums/112090240?uid=1&isSubCate=false&referrercate=3879491",
        "price": null
      }
    ],
    "count": 25
  },
  "bundesliga": {
    "name": "Bundesliga",
    "flag": "DE",
    "category_id": "3879521",
    "products": [
      {
        "name": "Augsburg",
        "image": "https://photo.yupoo.com/1to1jerseyworld/f25a6317/medium.jpg",
        "link": "https://1to1jerseyworld.x.yupoo.com/albums/200267614?uid=1&isSubCate=false&referrercate=3879521",
        "price": null
      },
      {
        "name": "1. FC Magdeburg",
        "image": "https://photo.yupoo.com/1to1jerseyworld/01c6f546/medium.jpg",
        "link": "https://1to1jerseyworld.x.yupoo.com/albums/197738148?uid=1&isSubCate=false&referrercate=3879521",
        "price": null
      },
      {
        "name": "1. FC Nürnberg",
        "image": "https://photo.yupoo.com/1to1jerseyworld/e5e83b44/medium.jpg",
        "link": "https://1to1jerseyworld.x.yupoo.com/albums/197737900?uid=1&isSubCate=false&referrercate=3879521",
        "price": null
      },
      {
        "name": "VfL Bochum",
        "image": "https://photo.yupoo.com/1to1jerseyworld/df5b3bde/medium.jpg",
        "link": "https://1to1jerseyworld.x.yupoo.com/albums/195119894?uid=1&isSubCate=false&referrercate=3879521",
        "price": null
      },
      {
        "name": "Holstein Kiel",
        "image": "https://photo.yupoo.com/1to1jerseyworld/91788368/medium.jpg",
        "link": "https://1to1jerseyworld.x.yupoo.com/albums/195119640?uid=1&isSubCate=false&referrercate=3879521",
        "price": null
      },
      {
        "name": "Hansa Rostock",
        "image": "https://photo.yupoo.com/1to1jerseyworld/7af6f85d/medium.jpg",
        "link": "https://1to1jerseyworld.x.yupoo.com/albums/195119248?uid=1&isSubCate=false&referrercate=3879521",
        "price": null
      },
      {
        "name": "Carl Zeiss Jena",
        "image": "https://photo.yupoo.com/1to1jerseyworld/e4a1ed63/medium.jpg",
        "link": "https://1to1jerseyworld.x.yupoo.com/albums/195118790?uid=1&isSubCate=false&referrercate=3879521",
        "price": null
      },
      {
        "name": "Arminia Bielefeld",
        "image": "https://photo.yupoo.com/1to1jerseyworld/94eb2c03/medium.jpg",
        "link": "https://1to1jerseyworld.x.yupoo.com/albums/195118023?uid=1&isSubCate=false&referrercate=3879521",
        "price": null
      },
      {
        "name": "Mainz 05",
        "image": "https://photo.yupoo.com/1to1jerseyworld/e5433c51/medium.jpg",
        "link": "https://1to1jerseyworld.x.yupoo.com/albums/191400833?uid=1&isSubCate=false&referrercate=3879521",
        "price": null
      },
      {
        "name": "SC Freiburg",
        "image": "https://photo.yupoo.com/1to1jerseyworld/cb7de749/medium.jpg",
        "link": "https://1to1jerseyworld.x.yupoo.com/albums/177995463?uid=1&isSubCate=false&referrercate=3879521",
        "price": null
      },
      {
        "name": "Fortuna Düsseldorf",
        "image": "https://photo.yupoo.com/1to1jerseyworld/59e94bfd/medium.jpg",
        "link": "https://1to1jerseyworld.x.yupoo.com/albums/173000067?uid=1&isSubCate=false&referrercate=3879521",
        "price": null
      },
      {
        "name": "Hamburger SV",
        "image": "https://photo.yupoo.com/1to1jerseyworld/93a1bb5a/medium.jpg",
        "link": "https://1to1jerseyworld.x.yupoo.com/albums/172533965?uid=1&isSubCate=false&referrercate=3879521",
        "price": null
      },
      {
        "name": "Wolfsburg",
        "image": "https://photo.yupoo.com/1to1jerseyworld/50f22d88/medium.jpg",
        "link": "https://1to1jerseyworld.x.yupoo.com/albums/169868045?uid=1&isSubCate=false&referrercate=3879521",
        "price": null
      },
      {
        "name": "Heidenheim",
        "image": "https://photo.yupoo.com/1to1jerseyworld/42204c42/medium.jpg",
        "link": "https://1to1jerseyworld.x.yupoo.com/albums/168961794?uid=1&isSubCate=false&referrercate=3879521",
        "price": null
      },
      {
        "name": "Bayer 04 Leverkusen",
        "image": "https://photo.yupoo.com/1to1jerseyworld/2b49b936/medium.jpg",
        "link": "https://1to1jerseyworld.x.yupoo.com/albums/147786215?uid=1&isSubCate=false&referrercate=3879521",
        "price": null
      },
      {
        "name": "FC Union Berlin",
        "image": "https://photo.yupoo.com/1to1jerseyworld/ca3fb634/medium.jpg",
        "link": "https://1to1jerseyworld.x.yupoo.com/albums/147578075?uid=1&isSubCate=false&referrercate=3879521",
        "price": null
      },
      {
        "name": "Schalke 04",
        "image": "https://photo.yupoo.com/1to1jerseyworld/728f0107/medium.jpg",
        "link": "https://1to1jerseyworld.x.yupoo.com/albums/139685243?uid=1&isSubCate=false&referrercate=3879521",
        "price": null
      },
      {
        "name": "Hertha BSC",
        "image": "https://photo.yupoo.com/1to1jerseyworld/8e3bb781/medium.jpg",
        "link": "https://1to1jerseyworld.x.yupoo.com/albums/139684612?uid=1&isSubCate=false&referrercate=3879521",
        "price": null
      },
      {
        "name": "St. Pauli",
        "image": "https://photo.yupoo.com/1to1jerseyworld/d3393ff6/medium.jpg",
        "link": "https://1to1jerseyworld.x.yupoo.com/albums/118369747?uid=1&isSubCate=false&referrercate=3879521",
        "price": null
      },
      {
        "name": "Borussia Mönchengladbach",
        "image": "https://photo.yupoo.com/1to1jerseyworld/db9e2a3d/medium.jpg",
        "link": "https://1to1jerseyworld.x.yupoo.com/albums/116083235?uid=1&isSubCate=false&referrercate=3879521",
        "price": null
      },
      {
        "name": "Werder Bremen",
        "image": "https://photo.yupoo.com/1to1jerseyworld/5c9dd1ec/medium.jpg",
        "link": "https://1to1jerseyworld.x.yupoo.com/albums/115220434?uid=1&isSubCate=false&referrercate=3879521",
        "price": null
      },
      {
        "name": "TSG 1899 Hoffenheim",
        "image": "https://photo.yupoo.com/1to1jerseyworld/bf0fd4eb/medium.jpg",
        "link": "https://1to1jerseyworld.x.yupoo.com/albums/113095410?uid=1&isSubCate=false&referrercate=3879521",
        "price": null
      },
      {
        "name": "Bayern",
        "image": "https://photo.yupoo.com/1to1jerseyworld/ee2140f3/medium.jpg",
        "link": "https://1to1jerseyworld.x.yupoo.com/albums/112091660?uid=1&isSubCate=false&referrercate=3879521",
        "price": null
      },
      {
        "name": "Dortmund",
        "image": "https://photo.yupoo.com/1to1jerseyworld/52d73614/medium.jpg",
        "link": "https://1to1jerseyworld.x.yupoo.com/albums/112091647?uid=1&isSubCate=false&referrercate=3879521",
        "price": null
      },
      {
        "name": "Frankfurt",
        "image": "https://photo.yupoo.com/1to1jerseyworld/f8393247/medium.jpg",
        "link": "https://1to1jerseyworld.x.yupoo.com/albums/112091634?uid=1&isSubCate=false&referrercate=3879521",
        "price": null
      },
      {
        "name": "RB Leipzig",
        "image": "https://photo.yupoo.com/1to1jerseyworld/19912136/medium.jpg",
        "link": "https://1to1jerseyworld.x.yupoo.com/albums/112091609?uid=1&isSubCate=false&referrercate=3879521",
        "price": null
      },
      {
        "name": "SpVgg Greuther Fürth",
        "image": "https://photo.yupoo.com/1to1jerseyworld/166974e1/medium.jpg",
        "link": "https://1to1jerseyworld.x.yupoo.com/albums/112091595?uid=1&isSubCate=false&referrercate=3879521",
        "price": null
      },
      {
        "name": "Köln",
        "image": "https://photo.yupoo.com/1to1jerseyworld/d8cd0fba/medium.jpg",
        "link": "https://1to1jerseyworld.x.yupoo.com/albums/112091583?uid=1&isSubCate=false&referrercate=3879521",
        "price": null
      },
      {
        "name": "Stuttgart",
        "image": "https://photo.yupoo.com/1to1jerseyworld/2a7e8666/medium.jpg",
        "link": "https://1to1jerseyworld.x.yupoo.com/albums/112091575?uid=1&isSubCate=false&referrercate=3879521",
        "price": null
      }
    ],
    "count": 29
  },
  "ligue-1": {
    "name": "Ligue 1",
    "flag": "FR",
    "category_id": "3879532",
    "products": [
      {
        "name": "AJ Auxerre",
        "image": "https://photo.yupoo.com/1to1jerseyworld/630a148b/medium.jpg",
        "link": "https://1to1jerseyworld.x.yupoo.com/albums/214663500?uid=1&isSubCate=false&referrercate=3879532",
        "price": null
      },
      {
        "name": "Paris FC",
        "image": "https://photo.yupoo.com/1to1jerseyworld/fa33dd6e/medium.jpg",
        "link": "https://1to1jerseyworld.x.yupoo.com/albums/213113063?uid=1&isSubCate=false&referrercate=3879532",
        "price": null
      },
      {
        "name": "Toulouse",
        "image": "https://photo.yupoo.com/1to1jerseyworld/33321bf5/medium.jpg",
        "link": "https://1to1jerseyworld.x.yupoo.com/albums/183801201?uid=1&isSubCate=false&referrercate=3879532",
        "price": null
      },
      {
        "name": "Versailles",
        "image": "https://photo.yupoo.com/1to1jerseyworld/b6c88a33/medium.jpg",
        "link": "https://1to1jerseyworld.x.yupoo.com/albums/181861023?uid=1&isSubCate=false&referrercate=3879532",
        "price": null
      },
      {
        "name": "Rennais F.C.",
        "image": "https://photo.yupoo.com/1to1jerseyworld/8fe0eeae/medium.jpg",
        "link": "https://1to1jerseyworld.x.yupoo.com/albums/116083320?uid=1&isSubCate=false&referrercate=3879532",
        "price": null
      },
      {
        "name": "PSG",
        "image": "https://photo.yupoo.com/1to1jerseyworld/2c6d73f2/medium.jpg",
        "link": "https://1to1jerseyworld.x.yupoo.com/albums/112092459?uid=1&isSubCate=false&referrercate=3879532",
        "price": null
      },
      {
        "name": "Marseille",
        "image": "https://photo.yupoo.com/1to1jerseyworld/5534a9ad/medium.jpg",
        "link": "https://1to1jerseyworld.x.yupoo.com/albums/112092456?uid=1&isSubCate=false&referrercate=3879532",
        "price": null
      },
      {
        "name": "Lille",
        "image": "https://photo.yupoo.com/1to1jerseyworld/a8829099/medium.jpg",
        "link": "https://1to1jerseyworld.x.yupoo.com/albums/112092452?uid=1&isSubCate=false&referrercate=3879532",
        "price": null
      },
      {
        "name": "Lyon",
        "image": "https://photo.yupoo.com/1to1jerseyworld/19b931fa/medium.jpg",
        "link": "https://1to1jerseyworld.x.yupoo.com/albums/112092446?uid=1&isSubCate=false&referrercate=3879532",
        "price": null
      },
      {
        "name": "Angers",
        "image": "https://photo.yupoo.com/1to1jerseyworld/237b79f9/medium.jpg",
        "link": "https://1to1jerseyworld.x.yupoo.com/albums/112092439?uid=1&isSubCate=false&referrercate=3879532",
        "price": null
      },
      {
        "name": "Lens",
        "image": "https://photo.yupoo.com/1to1jerseyworld/3c93b5f7/medium.jpg",
        "link": "https://1to1jerseyworld.x.yupoo.com/albums/112092433?uid=1&isSubCate=false&referrercate=3879532",
        "price": null
      },
      {
        "name": "Monaco",
        "image": "https://photo.yupoo.com/1to1jerseyworld/9ef7f274/medium.jpg",
        "link": "https://1to1jerseyworld.x.yupoo.com/albums/112092421?uid=1&isSubCate=false&referrercate=3879532",
        "price": null
      },
      {
        "name": "Nantes",
        "image": "https://photo.yupoo.com/1to1jerseyworld/93d024e6/medium.jpg",
        "link": "https://1to1jerseyworld.x.yupoo.com/albums/112092417?uid=1&isSubCate=false&referrercate=3879532",
        "price": null
      },
      {
        "name": "OGC Nice",
        "image": "https://photo.yupoo.com/1to1jerseyworld/5efda1ae/medium.jpg",
        "link": "https://1to1jerseyworld.x.yupoo.com/albums/112092413?uid=1&isSubCate=false&referrercate=3879532",
        "price": null
      },
      {
        "name": "Saint Etienne",
        "image": "https://photo.yupoo.com/1to1jerseyworld/1f3bb13b/medium.jpg",
        "link": "https://1to1jerseyworld.x.yupoo.com/albums/112092406?uid=1&isSubCate=false&referrercate=3879532",
        "price": null
      },
      {
        "name": "Strasbourg",
        "image": "https://photo.yupoo.com/1to1jerseyworld/9694edee/medium.jpg",
        "link": "https://1to1jerseyworld.x.yupoo.com/albums/112092401?uid=1&isSubCate=false&referrercate=3879532",
        "price": null
      },
      {
        "name": "Brest",
        "image": "https://photo.yupoo.com/1to1jerseyworld/be7dc02c/medium.jpg",
        "link": "https://1to1jerseyworld.x.yupoo.com/albums/112092391?uid=1&isSubCate=false&referrercate=3879532",
        "price": null
      },
      {
        "name": "Bordeaux",
        "image": "https://photo.yupoo.com/1to1jerseyworld/b4db0317/medium.jpg",
        "link": "https://1to1jerseyworld.x.yupoo.com/albums/112092387?uid=1&isSubCate=false&referrercate=3879532",
        "price": null
      }
    ],
    "count": 18
  },
  "outros": {
    "name": "Outros Clubes",
    "flag": "GL",
    "category_id": "outros",
    "products": [
      {
        "name": "Celtic FC",
        "image": "outros clubes/Celtic_FC_logo.png",
        "link": "#/product/gen_outros_celtic_home",
        "price": "349,90"
      },
      {
        "name": "PSV Eindhoven",
        "image": "outros clubes/PSV_Eindhoven_escudo.png",
        "link": "#/product/gen_outros_psv_home",
        "price": "349,90"
      },
      {
        "name": "Benfica",
        "image": "outros clubes/Sport_Lisboa_e_Benfica.svg.png",
        "link": "#/product/gen_outros_benfica_home",
        "price": "349,90"
      },
      {
        "name": "Sporting CP",
        "image": "https://images.unsplash.com/photo-1579952363873-27f3bade9f55?w=400",
        "link": "#/product/gen_outros_sporting_clube_home",
        "price": "349,90"
      },
      {
        "name": "FC Porto",
        "image": "outros clubes/F.C._Porto_logo.png",
        "link": "#/product/gen_outros_porto_home",
        "price": "349,90"
      },
      {
        "name": "Braga",
        "image": "outros clubes/150px-Sporting_Clube_Braga.png",
        "link": "#/product/gen_outros_braga_home",
        "price": "349,90"
      },
      {
        "name": "V. Guimarães",
        "image": "https://images.unsplash.com/photo-1579952363873-27f3bade9f55?w=400",
        "link": "#/product/gen_outros_guimaraes_home",
        "price": "349,90"
      },
      {
        "name": "Ajax",
        "image": "outros clubes/AFC_Ajax_Amsterdam.svg.png",
        "link": "#/product/gen_outros_ajax_home",
        "price": "349,90"
      },
      {
        "name": "Galatasaray",
        "image": "outros clubes/Galatasaray_Sports_Club_Logo.svg.png",
        "link": "#/product/gen_outros_galatasaray_home",
        "price": "349,90"
      },
      {
        "name": "Fenerbahçe",
        "image": "https://images.unsplash.com/photo-1579952363873-27f3bade9f55?w=400",
        "link": "#/product/gen_outros_fenerbahce_home",
        "price": "349,90"
      },
      {
        "name": "Boca Juniors",
        "image": "outros clubes/Boca_Juniors_logo18.svg.png",
        "link": "#/product/gen_outros_boca_juniors_home",
        "price": "349,90"
      },
      {
        "name": "River Plate",
        "image": "outros clubes/Club_Atlético_River_Plate_logo.svg.png",
        "link": "#/product/gen_outros_river_plate_home",
        "price": "349,90"
      },
      {
        "name": "Argentinos Juniors",
        "image": "https://images.unsplash.com/photo-1579952363873-27f3bade9f55?w=400",
        "link": "#/product/gen_outros_argentinos_jrs_home",
        "price": "349,90"
      },
      {
        "name": "Racing Club",
        "image": "outros clubes/Escudo_de_Racing_Club_(2014).svg.png",
        "link": "#/product/gen_outros_racing_club_home",
        "price": "349,90"
      },
      {
        "name": "Lanús",
        "image": "https://images.unsplash.com/photo-1579952363873-27f3bade9f55?w=400",
        "link": "#/product/gen_outros_lanus_home",
        "price": "349,90"
      },
      {
        "name": "Tigre",
        "image": "outros clubes/Escudo_del_Club_Atlético_Tigre_-_2019.svg.png",
        "link": "#/product/gen_outros_tigre_home",
        "price": "349,90"
      },
      {
        "name": "San Lorenzo",
        "image": "outros clubes/Escudo_del_Club_Atlético_San_Lorenzo_de_Almagro.png",
        "link": "#/product/gen_outros_san_lorenzo_home",
        "price": "349,90"
      },
      {
        "name": "Newell\\",
        "image": "https://images.unsplash.com/photo-1579952363873-27f3bade9f55?w=400",
        "link": "#/product/gen_outros_newells_home",
        "price": "349,90"
      },
      {
        "name": "Club América",
        "image": "https://images.unsplash.com/photo-1579952363873-27f3bade9f55?w=400",
        "link": "#/product/gen_outros_club_america_home",
        "price": "349,90"
      },
      {
        "name": "Chivas Guadalajara",
        "image": "outros clubes/Chivas-logo.png",
        "link": "#/product/gen_outros_chivas_home",
        "price": "349,90"
      },
      {
        "name": "Cruz Azul",
        "image": "outros clubes/Cruz_Azul_FC.svg.png",
        "link": "#/product/gen_outros_cruz_azul_home",
        "price": "349,90"
      },
      {
        "name": "Monterrey",
        "image": "outros clubes/CF_Monterrey_logo.png",
        "link": "#/product/gen_outros_monterrey_home",
        "price": "349,90"
      },
      {
        "name": "Toluca",
        "image": "outros clubes/Club_Toluca_Logo.svg.png",
        "link": "#/product/gen_outros_toluca_home",
        "price": "349,90"
      },
      {
        "name": "Tigres UANL",
        "image": "outros clubes/Escudo_del_Club_Atlético_Tigre_-_2019.svg.png",
        "link": "#/product/gen_outros_tigres_uanl_home",
        "price": "349,90"
      },
      {
        "name": "León",
        "image": "https://images.unsplash.com/photo-1579952363873-27f3bade9f55?w=400",
        "link": "#/product/gen_outros_leon_home",
        "price": "349,90"
      },
      {
        "name": "Pumas UNAM",
        "image": "outros clubes/Club_Universidad_Nacional_logo.svg.png",
        "link": "#/product/gen_outros_pumas_home",
        "price": "349,90"
      },
      {
        "name": "Atlas",
        "image": "outros clubes/Fútbol_Club_Atlas.svg.png",
        "link": "#/product/gen_outros_atlas_home",
        "price": "349,90"
      },
      {
        "name": "Necaxa",
        "image": "outros clubes/Club_Necaxa_Logo.svg.png",
        "link": "#/product/gen_outros_necaxa_home",
        "price": "349,90"
      },
      {
        "name": "U. de Chile",
        "image": "https://images.unsplash.com/photo-1579952363873-27f3bade9f55?w=400",
        "link": "#/product/gen_outros_u_de_chile_home",
        "price": "349,90"
      },
      {
        "name": "Colo Colo",
        "image": "outros clubes/Colo-Colo_Futbol_Club.png",
        "link": "#/product/gen_outros_colo_colo_home",
        "price": "349,90"
      },
      {
        "name": "Palestino",
        "image": "outros clubes/Escudo_Oficial_Palestino.png",
        "link": "#/product/gen_outros_palestino_home",
        "price": "349,90"
      },
      {
        "name": "América de Cali",
        "image": "https://images.unsplash.com/photo-1579952363873-27f3bade9f55?w=400",
        "link": "#/product/gen_outros_america_de_cali_home",
        "price": "349,90"
      },
      {
        "name": "Atlético Nacional",
        "image": "https://images.unsplash.com/photo-1579952363873-27f3bade9f55?w=400",
        "link": "#/product/gen_outros_atletico_nacional_home",
        "price": "349,90"
      },
      {
        "name": "Peñarol",
        "image": "https://images.unsplash.com/photo-1579952363873-27f3bade9f55?w=400",
        "link": "#/product/gen_outros_penarol_home",
        "price": "349,90"
      },
      {
        "name": "Nacional (URU)",
        "image": "https://images.unsplash.com/photo-1579952363873-27f3bade9f55?w=400",
        "link": "#/product/gen_outros_nacional_uru_home",
        "price": "349,90"
      },
      {
        "name": "Al-Nassr",
        "image": "https://images.unsplash.com/photo-1579952363873-27f3bade9f55?w=400",
        "link": "#/product/gen_outros_al_nassr_home",
        "price": "349,90"
      },
      {
        "name": "Al-Hilal",
        "image": "https://images.unsplash.com/photo-1579952363873-27f3bade9f55?w=400",
        "link": "#/product/gen_outros_al_hilal_home",
        "price": "349,90"
      },
      {
        "name": "Al-Ahli",
        "image": "https://images.unsplash.com/photo-1579952363873-27f3bade9f55?w=400",
        "link": "#/product/gen_outros_al_ahli_home",
        "price": "349,90"
      },
      {
        "name": "Al-Ittihad",
        "image": "https://images.unsplash.com/photo-1579952363873-27f3bade9f55?w=400",
        "link": "#/product/gen_outros_al_ittihad_home",
        "price": "349,90"
      },
      {
        "name": "Rangers FC",
        "image": "outros clubes/Rangers_FC_logo.svg.png",
        "link": "#/product/gen_outros_rangers_home",
        "price": "349,90"
      },
      {
        "name": "Panathinaikos",
        "image": "outros clubes/Panathinaikos_FC_logo.png",
        "link": "#/product/gen_outros_panathinaikos_home",
        "price": "349,90"
      },
      {
        "name": "Olympiacos",
        "image": "outros clubes/Olympiacos.png",
        "link": "#/product/gen_outros_olympiacos_home",
        "price": "349,90"
      },
      {
        "name": "Estrela Vermelha",
        "image": "outros clubes/OK_Crvena_Zvezda(logo).png",
        "link": "#/product/gen_outros_estrela_vermelha_home",
        "price": "349,90"
      },
      {
        "name": "Zenit",
        "image": "outros clubes/FC_Zenit_2_star_2023_logo.png",
        "link": "#/product/gen_outros_zenit_home",
        "price": "349,90"
      },
      {
        "name": "FC Copenhagen",
        "image": "outros clubes/FC_København.png",
        "link": "#/product/gen_outros_copenhagen_home",
        "price": "349,90"
      },
      {
        "name": "Hajduk Split",
        "image": "outros clubes/HNK_Hajduk_Split.png",
        "link": "#/product/gen_outros_hajduk_split_home",
        "price": "349,90"
      },
      {
        "name": "Real Salt Lake",
        "image": "outros clubes/Real_Salt_Lake.png",
        "link": "#/product/gen_outros_real_salt_lake_home",
        "price": "349,90"
      },
      {
        "name": "Nashville SC",
        "image": "outros clubes/Nashville_SC.png",
        "link": "#/product/gen_outros_nashville_home",
        "price": "349,90"
      }
    ],
    "count": 48
  },
  "selecoes": {
    "name": "Seleções Nacionais",
    "flag": "UN",
    "category_id": "selecoes",
    "products": [
      {
        "name": "Japão",
        "image": "https://images.unsplash.com/photo-1579952363873-27f3bade9f55?w=400",
        "link": "#/product/gen_outros_japao_home",
        "price": "349,90"
      },
      {
        "name": "Holanda",
        "image": "seleções/Netherlands_national_football_team_logo_2017.png",
        "link": "#/product/gen_selecoes_holanda_sel_home",
        "price": "349,90"
      },
      {
        "name": "França",
        "image": "https://images.unsplash.com/photo-1579952363873-27f3bade9f55?w=400",
        "link": "#/product/gen_selecoes_franca_sel_home",
        "price": "349,90"
      },
      {
        "name": "Colômbia",
        "image": "https://images.unsplash.com/photo-1579952363873-27f3bade9f55?w=400",
        "link": "#/product/gen_selecoes_colombia_sel_home",
        "price": "349,90"
      },
      {
        "name": "Inglaterra",
        "image": "seleções/inglaterra_selecao.png",
        "link": "#/product/gen_selecoes_inglaterra_sel_home",
        "price": "349,90"
      },
      {
        "name": "Suécia",
        "image": "https://images.unsplash.com/photo-1579952363873-27f3bade9f55?w=400",
        "link": "#/product/gen_selecoes_suecia_sel_home",
        "price": "349,90"
      },
      {
        "name": "Estados Unidos",
        "image": "https://images.unsplash.com/photo-1579952363873-27f3bade9f55?w=400",
        "link": "#/product/gen_selecoes_usa_sel_home",
        "price": "349,90"
      },
      {
        "name": "Espanha",
        "image": "seleções/Spain_National_Football_Team_badge.png",
        "link": "#/product/gen_selecoes_espanha_sel_home",
        "price": "349,90"
      },
      {
        "name": "Portugal",
        "image": "seleções/250px-Portugal_FPF.png",
        "link": "#/product/gen_selecoes_portugal_sel_home",
        "price": "349,90"
      },
      {
        "name": "Panamá",
        "image": "https://images.unsplash.com/photo-1579952363873-27f3bade9f55?w=400",
        "link": "#/product/gen_selecoes_panama_sel_home",
        "price": "349,90"
      },
      {
        "name": "Nigéria",
        "image": "https://images.unsplash.com/photo-1579952363873-27f3bade9f55?w=400",
        "link": "#/product/gen_selecoes_nigeria_sel_home",
        "price": "349,90"
      },
      {
        "name": "Brasil",
        "image": "seleções/Confederação_Brasileira_de_Futebol_logo_(2002).svg.png",
        "link": "#/product/gen_selecoes_brasil_sel_home",
        "price": "349,90"
      },
      {
        "name": "México",
        "image": "https://images.unsplash.com/photo-1579952363873-27f3bade9f55?w=400",
        "link": "#/product/gen_selecoes_mexico_sel_home",
        "price": "349,90"
      },
      {
        "name": "Alemanha",
        "image": "seleções/alemanha.png",
        "link": "#/product/gen_selecoes_alemanha_sel_home",
        "price": "349,90"
      },
      {
        "name": "Argentina",
        "image": "seleções/argentina.png",
        "link": "#/product/gen_selecoes_argentina_sel_home",
        "price": "349,90"
      },
      {
        "name": "Itália",
        "image": "https://images.unsplash.com/photo-1579952363873-27f3bade9f55?w=400",
        "link": "#/product/gen_selecoes_italia_sel_home",
        "price": "349,90"
      },
      {
        "name": "Turquia",
        "image": "seleções/TürkiyeFF.png",
        "link": "#/product/gen_selecoes_turquia_sel_home",
        "price": "349,90"
      },
      {
        "name": "Austrália",
        "image": "https://images.unsplash.com/photo-1579952363873-27f3bade9f55?w=400",
        "link": "#/product/gen_selecoes_australia_sel_home",
        "price": "349,90"
      },
      {
        "name": "Chile",
        "image": "seleções/Logo_Federación_de_Fútbol_de_Chile.png",
        "link": "#/product/gen_selecoes_chile_sel_home",
        "price": "349,90"
      },
      {
        "name": "Marrocos",
        "image": "seleções/Fédération_Royale_Marocaine_de_Football.png",
        "link": "#/product/gen_selecoes_marrocos_sel_home",
        "price": "349,90"
      },
      {
        "name": "Venezuela",
        "image": "seleções/Logotipo_de_la_Federación_Venezolana_de_Fútbol.svg.png",
        "link": "#/product/gen_selecoes_venezuela_sel_home",
        "price": "349,90"
      },
      {
        "name": "África do Sul",
        "image": "https://images.unsplash.com/photo-1579952363873-27f3bade9f55?w=400",
        "link": "#/product/gen_selecoes_africa_sul_sel_home",
        "price": "349,90"
      },
      {
        "name": "Peru",
        "image": "seleções/Logotipo_de_la_Federación_Peruana_de_Fútbol.svg.png",
        "link": "#/product/gen_selecoes_peru_sel_home",
        "price": "349,90"
      },
      {
        "name": "Paraguai",
        "image": "seleções/Asociación_Paraguaya_de_Fútbol_logo.svg.png",
        "link": "#/product/gen_selecoes_paraguai_sel_home",
        "price": "349,90"
      },
      {
        "name": "Grécia",
        "image": "https://images.unsplash.com/photo-1579952363873-27f3bade9f55?w=400",
        "link": "#/product/gen_selecoes_grecia_sel_home",
        "price": "349,90"
      },
      {
        "name": "Hungria",
        "image": "seleções/Magyar_Labdarúgó-Szövetség.png",
        "link": "#/product/gen_selecoes_hungria_sel_home",
        "price": "349,90"
      },
      {
        "name": "Costa Rica",
        "image": "seleções/Costa_Rica_national_football_team_logo.svg.png",
        "link": "#/product/gen_selecoes_costa_rica_sel_home",
        "price": "349,90"
      },
      {
        "name": "Canadá",
        "image": "https://images.unsplash.com/photo-1579952363873-27f3bade9f55?w=400",
        "link": "#/product/gen_selecoes_canada_sel_home",
        "price": "349,90"
      }
    ],
    "count": 28
  }
}